<?xml version="1.0" encoding="UTF-8" standalone="yes"?>
<template encoding-version="1.2">
    <description></description>
    <groupId>c8726ef7-0176-1000-ffff-ffff813a093d</groupId>
    <name>ETL_crypto_table</name>
    <snippet>
        <connections>
            <id>e4d75096-a1fc-32c2-0000-000000000000</id>
            <parentGroupId>4d60d1ce-d680-3376-0000-000000000000</parentGroupId>
            <backPressureDataSizeThreshold>1 GB</backPressureDataSizeThreshold>
            <backPressureObjectThreshold>10000</backPressureObjectThreshold>
            <destination>
                <groupId>4d60d1ce-d680-3376-0000-000000000000</groupId>
                <id>f7b82af9-01d6-3270-0000-000000000000</id>
                <type>PROCESSOR</type>
            </destination>
            <flowFileExpiration>0 sec</flowFileExpiration>
            <labelIndex>1</labelIndex>
            <name></name>
            <selectedRelationships>success</selectedRelationships>
            <source>
                <groupId>4d60d1ce-d680-3376-0000-000000000000</groupId>
                <id>6f0c7a53-9799-36e2-0000-000000000000</id>
                <type>PROCESSOR</type>
            </source>
            <zIndex>0</zIndex>
        </connections>
        <connections>
            <id>22838b65-dc0e-389d-0000-000000000000</id>
            <parentGroupId>4d60d1ce-d680-3376-0000-000000000000</parentGroupId>
            <backPressureDataSizeThreshold>1 GB</backPressureDataSizeThreshold>
            <backPressureObjectThreshold>10000</backPressureObjectThreshold>
            <destination>
                <groupId>4d60d1ce-d680-3376-0000-000000000000</groupId>
                <id>cc597665-6ea0-3dc8-0000-000000000000</id>
                <type>PROCESSOR</type>
            </destination>
            <flowFileExpiration>0 sec</flowFileExpiration>
            <labelIndex>1</labelIndex>
            <name></name>
            <selectedRelationships>failure</selectedRelationships>
            <selectedRelationships>splits</selectedRelationships>
            <source>
                <groupId>4d60d1ce-d680-3376-0000-000000000000</groupId>
                <id>f7b82af9-01d6-3270-0000-000000000000</id>
                <type>PROCESSOR</type>
            </source>
            <zIndex>0</zIndex>
        </connections>
        <connections>
            <id>2921cbbf-dec9-34eb-0000-000000000000</id>
            <parentGroupId>4d60d1ce-d680-3376-0000-000000000000</parentGroupId>
            <backPressureDataSizeThreshold>1 GB</backPressureDataSizeThreshold>
            <backPressureObjectThreshold>10000</backPressureObjectThreshold>
            <destination>
                <groupId>4d60d1ce-d680-3376-0000-000000000000</groupId>
                <id>c675be10-5870-3e20-0000-000000000000</id>
                <type>PROCESSOR</type>
            </destination>
            <flowFileExpiration>0 sec</flowFileExpiration>
            <labelIndex>1</labelIndex>
            <name></name>
            <selectedRelationships>matched</selectedRelationships>
            <source>
                <groupId>4d60d1ce-d680-3376-0000-000000000000</groupId>
                <id>0c27fd59-286b-38d8-0000-000000000000</id>
                <type>PROCESSOR</type>
            </source>
            <zIndex>0</zIndex>
        </connections>
        <connections>
            <id>472cc1cb-3dee-3f3f-0000-000000000000</id>
            <parentGroupId>4d60d1ce-d680-3376-0000-000000000000</parentGroupId>
            <backPressureDataSizeThreshold>1 GB</backPressureDataSizeThreshold>
            <backPressureObjectThreshold>10000</backPressureObjectThreshold>
            <destination>
                <groupId>4d60d1ce-d680-3376-0000-000000000000</groupId>
                <id>6c1c02b3-730a-3d71-0000-000000000000</id>
                <type>PROCESSOR</type>
            </destination>
            <flowFileExpiration>0 sec</flowFileExpiration>
            <labelIndex>1</labelIndex>
            <name></name>
            <selectedRelationships>success</selectedRelationships>
            <source>
                <groupId>4d60d1ce-d680-3376-0000-000000000000</groupId>
                <id>c675be10-5870-3e20-0000-000000000000</id>
                <type>PROCESSOR</type>
            </source>
            <zIndex>0</zIndex>
        </connections>
        <connections>
            <id>4b1bd05f-866e-3403-0000-000000000000</id>
            <parentGroupId>4d60d1ce-d680-3376-0000-000000000000</parentGroupId>
            <backPressureDataSizeThreshold>1 GB</backPressureDataSizeThreshold>
            <backPressureObjectThreshold>10000</backPressureObjectThreshold>
            <destination>
                <groupId>4d60d1ce-d680-3376-0000-000000000000</groupId>
                <id>0c27fd59-286b-38d8-0000-000000000000</id>
                <type>PROCESSOR</type>
            </destination>
            <flowFileExpiration>0 sec</flowFileExpiration>
            <labelIndex>1</labelIndex>
            <name></name>
            <selectedRelationships>Response</selectedRelationships>
            <source>
                <groupId>4d60d1ce-d680-3376-0000-000000000000</groupId>
                <id>883c045d-51b5-34e9-0000-000000000000</id>
                <type>PROCESSOR</type>
            </source>
            <zIndex>0</zIndex>
        </connections>
        <connections>
            <id>4c964eab-9b65-3d4a-0000-000000000000</id>
            <parentGroupId>4d60d1ce-d680-3376-0000-000000000000</parentGroupId>
            <backPressureDataSizeThreshold>1 GB</backPressureDataSizeThreshold>
            <backPressureObjectThreshold>10000</backPressureObjectThreshold>
            <destination>
                <groupId>4d60d1ce-d680-3376-0000-000000000000</groupId>
                <id>883c045d-51b5-34e9-0000-000000000000</id>
                <type>PROCESSOR</type>
            </destination>
            <flowFileExpiration>0 sec</flowFileExpiration>
            <labelIndex>1</labelIndex>
            <name></name>
            <selectedRelationships>matched</selectedRelationships>
            <source>
                <groupId>4d60d1ce-d680-3376-0000-000000000000</groupId>
                <id>cc597665-6ea0-3dc8-0000-000000000000</id>
                <type>PROCESSOR</type>
            </source>
            <zIndex>0</zIndex>
        </connections>
        <processors>
            <id>883c045d-51b5-34e9-0000-000000000000</id>
            <parentGroupId>4d60d1ce-d680-3376-0000-000000000000</parentGroupId>
            <position>
                <x>3.254452898462887</x>
                <y>204.91742143165447</y>
            </position>
            <bundle>
                <artifact>nifi-standard-nar</artifact>
                <group>org.apache.nifi</group>
                <version>1.5.0.3.1.2.0-7</version>
            </bundle>
            <config>
                <bulletinLevel>WARN</bulletinLevel>
                <comments></comments>
                <concurrentlySchedulableTaskCount>1</concurrentlySchedulableTaskCount>
                <descriptors>
                    <entry>
                        <key>HTTP Method</key>
                        <value>
                            <name>HTTP Method</name>
                        </value>
                    </entry>
                    <entry>
                        <key>Remote URL</key>
                        <value>
                            <name>Remote URL</name>
                        </value>
                    </entry>
                    <entry>
                        <key>SSL Context Service</key>
                        <value>
                            <identifiesControllerService>org.apache.nifi.ssl.SSLContextService</identifiesControllerService>
                            <name>SSL Context Service</name>
                        </value>
                    </entry>
                    <entry>
                        <key>Connection Timeout</key>
                        <value>
                            <name>Connection Timeout</name>
                        </value>
                    </entry>
                    <entry>
                        <key>Read Timeout</key>
                        <value>
                            <name>Read Timeout</name>
                        </value>
                    </entry>
                    <entry>
                        <key>Include Date Header</key>
                        <value>
                            <name>Include Date Header</name>
                        </value>
                    </entry>
                    <entry>
                        <key>Follow Redirects</key>
                        <value>
                            <name>Follow Redirects</name>
                        </value>
                    </entry>
                    <entry>
                        <key>Attributes to Send</key>
                        <value>
                            <name>Attributes to Send</name>
                        </value>
                    </entry>
                    <entry>
                        <key>Basic Authentication Username</key>
                        <value>
                            <name>Basic Authentication Username</name>
                        </value>
                    </entry>
                    <entry>
                        <key>Basic Authentication Password</key>
                        <value>
                            <name>Basic Authentication Password</name>
                        </value>
                    </entry>
                    <entry>
                        <key>Proxy Host</key>
                        <value>
                            <name>Proxy Host</name>
                        </value>
                    </entry>
                    <entry>
                        <key>Proxy Port</key>
                        <value>
                            <name>Proxy Port</name>
                        </value>
                    </entry>
                    <entry>
                        <key>Proxy Type</key>
                        <value>
                            <name>Proxy Type</name>
                        </value>
                    </entry>
                    <entry>
                        <key>invokehttp-proxy-user</key>
                        <value>
                            <name>invokehttp-proxy-user</name>
                        </value>
                    </entry>
                    <entry>
                        <key>invokehttp-proxy-password</key>
                        <value>
                            <name>invokehttp-proxy-password</name>
                        </value>
                    </entry>
                    <entry>
                        <key>Put Response Body In Attribute</key>
                        <value>
                            <name>Put Response Body In Attribute</name>
                        </value>
                    </entry>
                    <entry>
                        <key>Max Length To Put In Attribute</key>
                        <value>
                            <name>Max Length To Put In Attribute</name>
                        </value>
                    </entry>
                    <entry>
                        <key>Digest Authentication</key>
                        <value>
                            <name>Digest Authentication</name>
                        </value>
                    </entry>
                    <entry>
                        <key>Always Output Response</key>
                        <value>
                            <name>Always Output Response</name>
                        </value>
                    </entry>
                    <entry>
                        <key>Trusted Hostname</key>
                        <value>
                            <name>Trusted Hostname</name>
                        </value>
                    </entry>
                    <entry>
                        <key>Add Response Headers to Request</key>
                        <value>
                            <name>Add Response Headers to Request</name>
                        </value>
                    </entry>
                    <entry>
                        <key>Content-Type</key>
                        <value>
                            <name>Content-Type</name>
                        </value>
                    </entry>
                    <entry>
                        <key>send-message-body</key>
                        <value>
                            <name>send-message-body</name>
                        </value>
                    </entry>
                    <entry>
                        <key>Use Chunked Encoding</key>
                        <value>
                            <name>Use Chunked Encoding</name>
                        </value>
                    </entry>
                    <entry>
                        <key>Penalize on "No Retry"</key>
                        <value>
                            <name>Penalize on "No Retry"</name>
                        </value>
                    </entry>
                </descriptors>
                <executionNode>ALL</executionNode>
                <lossTolerant>false</lossTolerant>
                <penaltyDuration>30 sec</penaltyDuration>
                <properties>
                    <entry>
                        <key>HTTP Method</key>
                        <value>GET</value>
                    </entry>
                    <entry>
                        <key>Remote URL</key>
                        <value>${URL}</value>
                    </entry>
                    <entry>
                        <key>SSL Context Service</key>
                    </entry>
                    <entry>
                        <key>Connection Timeout</key>
                        <value>5 secs</value>
                    </entry>
                    <entry>
                        <key>Read Timeout</key>
                        <value>15 secs</value>
                    </entry>
                    <entry>
                        <key>Include Date Header</key>
                        <value>True</value>
                    </entry>
                    <entry>
                        <key>Follow Redirects</key>
                        <value>True</value>
                    </entry>
                    <entry>
                        <key>Attributes to Send</key>
                    </entry>
                    <entry>
                        <key>Basic Authentication Username</key>
                    </entry>
                    <entry>
                        <key>Basic Authentication Password</key>
                    </entry>
                    <entry>
                        <key>Proxy Host</key>
                    </entry>
                    <entry>
                        <key>Proxy Port</key>
                    </entry>
                    <entry>
                        <key>Proxy Type</key>
                        <value>http</value>
                    </entry>
                    <entry>
                        <key>invokehttp-proxy-user</key>
                    </entry>
                    <entry>
                        <key>invokehttp-proxy-password</key>
                    </entry>
                    <entry>
                        <key>Put Response Body In Attribute</key>
                    </entry>
                    <entry>
                        <key>Max Length To Put In Attribute</key>
                        <value>256</value>
                    </entry>
                    <entry>
                        <key>Digest Authentication</key>
                        <value>false</value>
                    </entry>
                    <entry>
                        <key>Always Output Response</key>
                        <value>false</value>
                    </entry>
                    <entry>
                        <key>Trusted Hostname</key>
                    </entry>
                    <entry>
                        <key>Add Response Headers to Request</key>
                        <value>false</value>
                    </entry>
                    <entry>
                        <key>Content-Type</key>
                        <value>${mime.type}</value>
                    </entry>
                    <entry>
                        <key>send-message-body</key>
                        <value>true</value>
                    </entry>
                    <entry>
                        <key>Use Chunked Encoding</key>
                        <value>false</value>
                    </entry>
                    <entry>
                        <key>Penalize on "No Retry"</key>
                        <value>false</value>
                    </entry>
                </properties>
                <runDurationMillis>0</runDurationMillis>
                <schedulingPeriod>0 sec</schedulingPeriod>
                <schedulingStrategy>TIMER_DRIVEN</schedulingStrategy>
                <yieldDuration>1 sec</yieldDuration>
            </config>
            <name>InvokeHTTP</name>
            <relationships>
                <autoTerminate>true</autoTerminate>
                <name>Failure</name>
            </relationships>
            <relationships>
                <autoTerminate>true</autoTerminate>
                <name>No Retry</name>
            </relationships>
            <relationships>
                <autoTerminate>true</autoTerminate>
                <name>Original</name>
            </relationships>
            <relationships>
                <autoTerminate>false</autoTerminate>
                <name>Response</name>
            </relationships>
            <relationships>
                <autoTerminate>true</autoTerminate>
                <name>Retry</name>
            </relationships>
            <state>STOPPED</state>
            <style/>
            <type>org.apache.nifi.processors.standard.InvokeHTTP</type>
        </processors>
        <processors>
            <id>c675be10-5870-3e20-0000-000000000000</id>
            <parentGroupId>4d60d1ce-d680-3376-0000-000000000000</parentGroupId>
            <position>
                <x>644.7240611817679</x>
                <y>445.78025822750965</y>
            </position>
            <bundle>
                <artifact>nifi-update-attribute-nar</artifact>
                <group>org.apache.nifi</group>
                <version>1.5.0.3.1.2.0-7</version>
            </bundle>
            <config>
                <bulletinLevel>WARN</bulletinLevel>
                <comments></comments>
                <concurrentlySchedulableTaskCount>1</concurrentlySchedulableTaskCount>
                <descriptors>
                    <entry>
                        <key>Delete Attributes Expression</key>
                        <value>
                            <name>Delete Attributes Expression</name>
                        </value>
                    </entry>
                    <entry>
                        <key>Store State</key>
                        <value>
                            <name>Store State</name>
                        </value>
                    </entry>
                    <entry>
                        <key>Stateful Variables Initial Value</key>
                        <value>
                            <name>Stateful Variables Initial Value</name>
                        </value>
                    </entry>
                    <entry>
                        <key>newDate</key>
                        <value>
                            <name>newDate</name>
                        </value>
                    </entry>
                </descriptors>
                <executionNode>ALL</executionNode>
                <lossTolerant>false</lossTolerant>
                <penaltyDuration>30 sec</penaltyDuration>
                <properties>
                    <entry>
                        <key>Delete Attributes Expression</key>
                    </entry>
                    <entry>
                        <key>Store State</key>
                        <value>Do not store state</value>
                    </entry>
                    <entry>
                        <key>Stateful Variables Initial Value</key>
                    </entry>
                    <entry>
                        <key>newDate</key>
                        <value>${date:toNumber():multiply(1000):format("yyyy-MM-dd", "GMT")}</value>
                    </entry>
                </properties>
                <runDurationMillis>0</runDurationMillis>
                <schedulingPeriod>0 sec</schedulingPeriod>
                <schedulingStrategy>TIMER_DRIVEN</schedulingStrategy>
                <yieldDuration>1 sec</yieldDuration>
            </config>
            <name>UpdateAttribute</name>
            <relationships>
                <autoTerminate>false</autoTerminate>
                <name>success</name>
            </relationships>
            <state>STOPPED</state>
            <style/>
            <type>org.apache.nifi.processors.attributes.UpdateAttribute</type>
        </processors>
        <processors>
            <id>cc597665-6ea0-3dc8-0000-000000000000</id>
            <parentGroupId>4d60d1ce-d680-3376-0000-000000000000</parentGroupId>
            <position>
                <x>642.8886996253059</x>
                <y>238.6366124389491</y>
            </position>
            <bundle>
                <artifact>nifi-standard-nar</artifact>
                <group>org.apache.nifi</group>
                <version>1.5.0.3.1.2.0-7</version>
            </bundle>
            <config>
                <bulletinLevel>WARN</bulletinLevel>
                <comments></comments>
                <concurrentlySchedulableTaskCount>1</concurrentlySchedulableTaskCount>
                <descriptors>
                    <entry>
                        <key>Character Set</key>
                        <value>
                            <name>Character Set</name>
                        </value>
                    </entry>
                    <entry>
                        <key>Maximum Buffer Size</key>
                        <value>
                            <name>Maximum Buffer Size</name>
                        </value>
                    </entry>
                    <entry>
                        <key>Maximum Capture Group Length</key>
                        <value>
                            <name>Maximum Capture Group Length</name>
                        </value>
                    </entry>
                    <entry>
                        <key>Enable Canonical Equivalence</key>
                        <value>
                            <name>Enable Canonical Equivalence</name>
                        </value>
                    </entry>
                    <entry>
                        <key>Enable Case-insensitive Matching</key>
                        <value>
                            <name>Enable Case-insensitive Matching</name>
                        </value>
                    </entry>
                    <entry>
                        <key>Permit Whitespace and Comments in Pattern</key>
                        <value>
                            <name>Permit Whitespace and Comments in Pattern</name>
                        </value>
                    </entry>
                    <entry>
                        <key>Enable DOTALL Mode</key>
                        <value>
                            <name>Enable DOTALL Mode</name>
                        </value>
                    </entry>
                    <entry>
                        <key>Enable Literal Parsing of the Pattern</key>
                        <value>
                            <name>Enable Literal Parsing of the Pattern</name>
                        </value>
                    </entry>
                    <entry>
                        <key>Enable Multiline Mode</key>
                        <value>
                            <name>Enable Multiline Mode</name>
                        </value>
                    </entry>
                    <entry>
                        <key>Enable Unicode-aware Case Folding</key>
                        <value>
                            <name>Enable Unicode-aware Case Folding</name>
                        </value>
                    </entry>
                    <entry>
                        <key>Enable Unicode Predefined Character Classes</key>
                        <value>
                            <name>Enable Unicode Predefined Character Classes</name>
                        </value>
                    </entry>
                    <entry>
                        <key>Enable Unix Lines Mode</key>
                        <value>
                            <name>Enable Unix Lines Mode</name>
                        </value>
                    </entry>
                    <entry>
                        <key>Include Capture Group 0</key>
                        <value>
                            <name>Include Capture Group 0</name>
                        </value>
                    </entry>
                    <entry>
                        <key>extract-text-enable-repeating-capture-group</key>
                        <value>
                            <name>extract-text-enable-repeating-capture-group</name>
                        </value>
                    </entry>
                    <entry>
                        <key>URL</key>
                        <value>
                            <name>URL</name>
                        </value>
                    </entry>
                </descriptors>
                <executionNode>ALL</executionNode>
                <lossTolerant>false</lossTolerant>
                <penaltyDuration>30 sec</penaltyDuration>
                <properties>
                    <entry>
                        <key>Character Set</key>
                        <value>UTF-8</value>
                    </entry>
                    <entry>
                        <key>Maximum Buffer Size</key>
                        <value>1 MB</value>
                    </entry>
                    <entry>
                        <key>Maximum Capture Group Length</key>
                        <value>1024</value>
                    </entry>
                    <entry>
                        <key>Enable Canonical Equivalence</key>
                        <value>false</value>
                    </entry>
                    <entry>
                        <key>Enable Case-insensitive Matching</key>
                        <value>false</value>
                    </entry>
                    <entry>
                        <key>Permit Whitespace and Comments in Pattern</key>
                        <value>false</value>
                    </entry>
                    <entry>
                        <key>Enable DOTALL Mode</key>
                        <value>false</value>
                    </entry>
                    <entry>
                        <key>Enable Literal Parsing of the Pattern</key>
                        <value>false</value>
                    </entry>
                    <entry>
                        <key>Enable Multiline Mode</key>
                        <value>false</value>
                    </entry>
                    <entry>
                        <key>Enable Unicode-aware Case Folding</key>
                        <value>false</value>
                    </entry>
                    <entry>
                        <key>Enable Unicode Predefined Character Classes</key>
                        <value>false</value>
                    </entry>
                    <entry>
                        <key>Enable Unix Lines Mode</key>
                        <value>false</value>
                    </entry>
                    <entry>
                        <key>Include Capture Group 0</key>
                        <value>true</value>
                    </entry>
                    <entry>
                        <key>extract-text-enable-repeating-capture-group</key>
                        <value>false</value>
                    </entry>
                    <entry>
                        <key>URL</key>
                        <value>(.*)</value>
                    </entry>
                </properties>
                <runDurationMillis>0</runDurationMillis>
                <schedulingPeriod>0 sec</schedulingPeriod>
                <schedulingStrategy>TIMER_DRIVEN</schedulingStrategy>
                <yieldDuration>1 sec</yieldDuration>
            </config>
            <name>ExtractText</name>
            <relationships>
                <autoTerminate>false</autoTerminate>
                <name>matched</name>
            </relationships>
            <relationships>
                <autoTerminate>true</autoTerminate>
                <name>unmatched</name>
            </relationships>
            <state>STOPPED</state>
            <style/>
            <type>org.apache.nifi.processors.standard.ExtractText</type>
        </processors>
        <processors>
            <id>f7b82af9-01d6-3270-0000-000000000000</id>
            <parentGroupId>4d60d1ce-d680-3376-0000-000000000000</parentGroupId>
            <position>
                <x>642.7034119434038</x>
                <y>2.424468994140625</y>
            </position>
            <bundle>
                <artifact>nifi-standard-nar</artifact>
                <group>org.apache.nifi</group>
                <version>1.5.0.3.1.2.0-7</version>
            </bundle>
            <config>
                <bulletinLevel>WARN</bulletinLevel>
                <comments></comments>
                <concurrentlySchedulableTaskCount>1</concurrentlySchedulableTaskCount>
                <descriptors>
                    <entry>
                        <key>Line Split Count</key>
                        <value>
                            <name>Line Split Count</name>
                        </value>
                    </entry>
                    <entry>
                        <key>Maximum Fragment Size</key>
                        <value>
                            <name>Maximum Fragment Size</name>
                        </value>
                    </entry>
                    <entry>
                        <key>Header Line Count</key>
                        <value>
                            <name>Header Line Count</name>
                        </value>
                    </entry>
                    <entry>
                        <key>Header Line Marker Characters</key>
                        <value>
                            <name>Header Line Marker Characters</name>
                        </value>
                    </entry>
                    <entry>
                        <key>Remove Trailing Newlines</key>
                        <value>
                            <name>Remove Trailing Newlines</name>
                        </value>
                    </entry>
                </descriptors>
                <executionNode>ALL</executionNode>
                <lossTolerant>false</lossTolerant>
                <penaltyDuration>30 sec</penaltyDuration>
                <properties>
                    <entry>
                        <key>Line Split Count</key>
                        <value>1</value>
                    </entry>
                    <entry>
                        <key>Maximum Fragment Size</key>
                    </entry>
                    <entry>
                        <key>Header Line Count</key>
                        <value>0</value>
                    </entry>
                    <entry>
                        <key>Header Line Marker Characters</key>
                    </entry>
                    <entry>
                        <key>Remove Trailing Newlines</key>
                        <value>true</value>
                    </entry>
                </properties>
                <runDurationMillis>0</runDurationMillis>
                <schedulingPeriod>0 sec</schedulingPeriod>
                <schedulingStrategy>TIMER_DRIVEN</schedulingStrategy>
                <yieldDuration>1 sec</yieldDuration>
            </config>
            <name>SplitText</name>
            <relationships>
                <autoTerminate>false</autoTerminate>
                <name>failure</name>
            </relationships>
            <relationships>
                <autoTerminate>true</autoTerminate>
                <name>original</name>
            </relationships>
            <relationships>
                <autoTerminate>false</autoTerminate>
                <name>splits</name>
            </relationships>
            <state>STOPPED</state>
            <style/>
            <type>org.apache.nifi.processors.standard.SplitText</type>
        </processors>
        <processors>
            <id>0c27fd59-286b-38d8-0000-000000000000</id>
            <parentGroupId>4d60d1ce-d680-3376-0000-000000000000</parentGroupId>
            <position>
                <x>0.0</x>
                <y>439.7525202940858</y>
            </position>
            <bundle>
                <artifact>nifi-standard-nar</artifact>
                <group>org.apache.nifi</group>
                <version>1.5.0.3.1.2.0-7</version>
            </bundle>
            <config>
                <bulletinLevel>WARN</bulletinLevel>
                <comments></comments>
                <concurrentlySchedulableTaskCount>1</concurrentlySchedulableTaskCount>
                <descriptors>
                    <entry>
                        <key>Destination</key>
                        <value>
                            <name>Destination</name>
                        </value>
                    </entry>
                    <entry>
                        <key>Return Type</key>
                        <value>
                            <name>Return Type</name>
                        </value>
                    </entry>
                    <entry>
                        <key>Path Not Found Behavior</key>
                        <value>
                            <name>Path Not Found Behavior</name>
                        </value>
                    </entry>
                    <entry>
                        <key>Null Value Representation</key>
                        <value>
                            <name>Null Value Representation</name>
                        </value>
                    </entry>
                    <entry>
                        <key>adjclose</key>
                        <value>
                            <name>adjclose</name>
                        </value>
                    </entry>
                    <entry>
                        <key>close</key>
                        <value>
                            <name>close</name>
                        </value>
                    </entry>
                    <entry>
                        <key>date</key>
                        <value>
                            <name>date</name>
                        </value>
                    </entry>
                    <entry>
                        <key>high</key>
                        <value>
                            <name>high</name>
                        </value>
                    </entry>
                    <entry>
                        <key>low</key>
                        <value>
                            <name>low</name>
                        </value>
                    </entry>
                    <entry>
                        <key>open</key>
                        <value>
                            <name>open</name>
                        </value>
                    </entry>
                    <entry>
                        <key>ticker</key>
                        <value>
                            <name>ticker</name>
                        </value>
                    </entry>
                    <entry>
                        <key>volume</key>
                        <value>
                            <name>volume</name>
                        </value>
                    </entry>
                </descriptors>
                <executionNode>ALL</executionNode>
                <lossTolerant>false</lossTolerant>
                <penaltyDuration>30 sec</penaltyDuration>
                <properties>
                    <entry>
                        <key>Destination</key>
                        <value>flowfile-attribute</value>
                    </entry>
                    <entry>
                        <key>Return Type</key>
                        <value>auto-detect</value>
                    </entry>
                    <entry>
                        <key>Path Not Found Behavior</key>
                        <value>ignore</value>
                    </entry>
                    <entry>
                        <key>Null Value Representation</key>
                        <value>empty string</value>
                    </entry>
                    <entry>
                        <key>adjclose</key>
                        <value>$.chart.result[0].indicators.adjclose[0].adjclose[0]</value>
                    </entry>
                    <entry>
                        <key>close</key>
                        <value>$.chart.result[0].indicators.quote[0].close[0]</value>
                    </entry>
                    <entry>
                        <key>date</key>
                        <value>$.chart.result[0].meta.currentTradingPeriod.post.end</value>
                    </entry>
                    <entry>
                        <key>high</key>
                        <value>$.chart.result[0].indicators.quote[0].high[0]</value>
                    </entry>
                    <entry>
                        <key>low</key>
                        <value>$.chart.result[0].indicators.quote[0].low[0]</value>
                    </entry>
                    <entry>
                        <key>open</key>
                        <value>$.chart.result[0].indicators.quote[0].open[0]</value>
                    </entry>
                    <entry>
                        <key>ticker</key>
                        <value>$.chart.result[0].meta.symbol</value>
                    </entry>
                    <entry>
                        <key>volume</key>
                        <value>$.chart.result[0].indicators.quote[0].volume[0]</value>
                    </entry>
                </properties>
                <runDurationMillis>0</runDurationMillis>
                <schedulingPeriod>0 sec</schedulingPeriod>
                <schedulingStrategy>TIMER_DRIVEN</schedulingStrategy>
                <yieldDuration>1 sec</yieldDuration>
            </config>
            <name>EvaluateJsonPath</name>
            <relationships>
                <autoTerminate>true</autoTerminate>
                <name>failure</name>
            </relationships>
            <relationships>
                <autoTerminate>false</autoTerminate>
                <name>matched</name>
            </relationships>
            <relationships>
                <autoTerminate>true</autoTerminate>
                <name>unmatched</name>
            </relationships>
            <state>STOPPED</state>
            <style/>
            <type>org.apache.nifi.processors.standard.EvaluateJsonPath</type>
        </processors>
        <processors>
            <id>6c1c02b3-730a-3d71-0000-000000000000</id>
            <parentGroupId>4d60d1ce-d680-3376-0000-000000000000</parentGroupId>
            <position>
                <x>645.3717805885035</x>
                <y>661.8940548056505</y>
            </position>
            <bundle>
                <artifact>nifi-standard-nar</artifact>
                <group>org.apache.nifi</group>
                <version>1.5.0.3.1.2.0-7</version>
            </bundle>
            <config>
                <bulletinLevel>WARN</bulletinLevel>
                <comments></comments>
                <concurrentlySchedulableTaskCount>1</concurrentlySchedulableTaskCount>
                <descriptors>
                    <entry>
                        <key>Regular Expression</key>
                        <value>
                            <name>Regular Expression</name>
                        </value>
                    </entry>
                    <entry>
                        <key>Replacement Value</key>
                        <value>
                            <name>Replacement Value</name>
                        </value>
                    </entry>
                    <entry>
                        <key>Character Set</key>
                        <value>
                            <name>Character Set</name>
                        </value>
                    </entry>
                    <entry>
                        <key>Maximum Buffer Size</key>
                        <value>
                            <name>Maximum Buffer Size</name>
                        </value>
                    </entry>
                    <entry>
                        <key>Replacement Strategy</key>
                        <value>
                            <name>Replacement Strategy</name>
                        </value>
                    </entry>
                    <entry>
                        <key>Evaluation Mode</key>
                        <value>
                            <name>Evaluation Mode</name>
                        </value>
                    </entry>
                </descriptors>
                <executionNode>ALL</executionNode>
                <lossTolerant>false</lossTolerant>
                <penaltyDuration>30 sec</penaltyDuration>
                <properties>
                    <entry>
                        <key>Regular Expression</key>
                        <value></value>
                    </entry>
                    <entry>
                        <key>Replacement Value</key>
                        <value>insert into stockexchange.Cryptocurrency values(from_unixtime(${date}, 'yyyy-MM-dd'),${open},${high},${low},${close},${adjclose},${volume},"${ticker}")</value>
                    </entry>
                    <entry>
                        <key>Character Set</key>
                        <value>UTF-8</value>
                    </entry>
                    <entry>
                        <key>Maximum Buffer Size</key>
                        <value>1 MB</value>
                    </entry>
                    <entry>
                        <key>Replacement Strategy</key>
                        <value>Always Replace</value>
                    </entry>
                    <entry>
                        <key>Evaluation Mode</key>
                        <value>Entire text</value>
                    </entry>
                </properties>
                <runDurationMillis>0</runDurationMillis>
                <schedulingPeriod>0 sec</schedulingPeriod>
                <schedulingStrategy>TIMER_DRIVEN</schedulingStrategy>
                <yieldDuration>1 sec</yieldDuration>
            </config>
            <name>ReplaceText</name>
            <relationships>
                <autoTerminate>true</autoTerminate>
                <name>failure</name>
            </relationships>
            <relationships>
                <autoTerminate>false</autoTerminate>
                <name>success</name>
            </relationships>
            <state>STOPPED</state>
            <style/>
            <type>org.apache.nifi.processors.standard.ReplaceText</type>
        </processors>
        <processors>
            <id>6f0c7a53-9799-36e2-0000-000000000000</id>
            <parentGroupId>4d60d1ce-d680-3376-0000-000000000000</parentGroupId>
            <position>
                <x>24.456402666060058</x>
                <y>0.0</y>
            </position>
            <bundle>
                <artifact>nifi-standard-nar</artifact>
                <group>org.apache.nifi</group>
                <version>1.5.0.3.1.2.0-7</version>
            </bundle>
            <config>
                <bulletinLevel>WARN</bulletinLevel>
                <comments></comments>
                <concurrentlySchedulableTaskCount>1</concurrentlySchedulableTaskCount>
                <descriptors>
                    <entry>
                        <key>File Size</key>
                        <value>
                            <name>File Size</name>
                        </value>
                    </entry>
                    <entry>
                        <key>Batch Size</key>
                        <value>
                            <name>Batch Size</name>
                        </value>
                    </entry>
                    <entry>
                        <key>Data Format</key>
                        <value>
                            <name>Data Format</name>
                        </value>
                    </entry>
                    <entry>
                        <key>Unique FlowFiles</key>
                        <value>
                            <name>Unique FlowFiles</name>
                        </value>
                    </entry>
                    <entry>
                        <key>generate-ff-custom-text</key>
                        <value>
                            <name>generate-ff-custom-text</name>
                        </value>
                    </entry>
                    <entry>
                        <key>character-set</key>
                        <value>
                            <name>character-set</name>
                        </value>
                    </entry>
                </descriptors>
                <executionNode>ALL</executionNode>
                <lossTolerant>false</lossTolerant>
                <penaltyDuration>30 sec</penaltyDuration>
                <properties>
                    <entry>
                        <key>File Size</key>
                        <value>0B</value>
                    </entry>
                    <entry>
                        <key>Batch Size</key>
                        <value>1</value>
                    </entry>
                    <entry>
                        <key>Data Format</key>
                        <value>Text</value>
                    </entry>
                    <entry>
                        <key>Unique FlowFiles</key>
                        <value>false</value>
                    </entry>
                    <entry>
                        <key>generate-ff-custom-text</key>
                        <value>https://query1.finance.yahoo.com/v8/finance/chart/BTC-USD?symbol=BTC-USD&amp;interval=1d
https://query1.finance.yahoo.com/v8/finance/chart/ETH-USD?symbol=ETH-USD&amp;interval=1d
https://query1.finance.yahoo.com/v8/finance/chart/XRP-USD?symbol=XRP-USD&amp;interval=1d
https://query1.finance.yahoo.com/v8/finance/chart/LTC-USD?symbol=LTC-USD&amp;interval=1d</value>
                    </entry>
                    <entry>
                        <key>character-set</key>
                        <value>UTF-8</value>
                    </entry>
                </properties>
                <runDurationMillis>0</runDurationMillis>
                <schedulingPeriod>1 day</schedulingPeriod>
                <schedulingStrategy>TIMER_DRIVEN</schedulingStrategy>
                <yieldDuration>1 day</yieldDuration>
            </config>
            <name>GenerateFlowFile</name>
            <relationships>
                <autoTerminate>false</autoTerminate>
                <name>success</name>
            </relationships>
            <state>STOPPED</state>
            <style/>
            <type>org.apache.nifi.processors.standard.GenerateFlowFile</type>
        </processors>
    </snippet>
    <timestamp>01/03/2021 16:33:42 UTC</timestamp>
</template>
